aztools/__init__.py
aztools/defender.py
aztools/loganalytics.py
aztools/oauth.py
hw2aztools-1.0.dist-info/licenses/LICENSE
hw2aztools-1.0.dist-info/METADATA
hw2aztools-1.0.dist-info/WHEEL
hw2aztools-1.0.dist-info/top_level.txt
hw2aztools-1.0.dist-info/RECORD
