Metadata-Version: 2.4
Name: hw2aztools
Version: 1.0
Summary: Modules to Interact with Azure API
Author: Harvey Wargo
Project-URL: Homepage, https://github.com/harveywargo2/hw2aztools
Keywords: Azure,Sentinel,MDE,M365D,Defender
Classifier: Programming Language :: Python
Classifier: Programming Language :: Python :: 3
Requires-Python: >=3.8
License-File: LICENSE
Requires-Dist: requests
Requires-Dist: pandas
Requires-Dist: datetime
Requires-Dist: jupyterlab
Dynamic: license-file
